pycmodels/__init__.py
pycmodels/config.py
pycmodels/logger.py
pycmodels-0.1.0.dist-info/LICENSE
pycmodels-0.1.0.dist-info/WHEEL
pycmodels-0.1.0.dist-info/METADATA
pycmodels-0.1.0.dist-info/RECORD
