Metadata-Version: 2.1
Name: pycmodels
Version: 0.1.0
Summary: A python library for simulating multiples models of computation.
Author: Luis Papiernik
Author-email: lpapiernik24@gmail.com
Requires-Python: >=3.8,<4.0
Classifier: Programming Language :: Python :: 3
Classifier: Programming Language :: Python :: 3.10
Classifier: Programming Language :: Python :: 3.8
Classifier: Programming Language :: Python :: 3.9
